{
    "map": {
        "2780:2775": {
            "x": 2780,
            "y": 2775,
            "object_code": "blue_ball"
        },
        "2771:2774": {
            "x": 2771,
            "y": 2774,
            "object_code": "green_ball"
        },
        "2775:2783": {
            "x": 2775,
            "y": 2783,
            "object_code": "red_ball"
        },
        "2791:2773": {
            "x": 2791,
            "y": 2773,
            "object_code": "red_ball"
        },
        "2781:2770": {
            "x": 2781,
            "y": 2770,
            "object_code": "green_ball"
        },
        "2769:2780": {
            "x": 2769,
            "y": 2780,
            "object_code": "cyan_ball"
        },
        "2786:2781": {
            "x": 2786,
            "y": 2781,
            "object_code": "yellow_ball"
        }
    },
    "player_position": {
        "x": 2777,
        "y": 2777
    },
    "min_score_to_win": 25,
    "time_limit": null,
    "max_speed": 150,
    "acceleration": 12,
    "zoom_value": 10,
    "add_powers": false,
    "map_edge_type": "deadly",
    "edge_distance": 300,
    "next_level":"{{home}}/37.json",
    "slow_time": "0.5",
    "slow_time_duration": "1",
    "size_power": "20",
    "size_power_duration": "1",
    "speed_power": "2",
    "speed_power_duration": "1"
}